salesforce_bulk_python/__init__.py
salesforce_bulk_python/bulk.py
salesforce_bulk_python-0.1.0.dist-info/LICENSE
salesforce_bulk_python-0.1.0.dist-info/METADATA
salesforce_bulk_python-0.1.0.dist-info/WHEEL
salesforce_bulk_python-0.1.0.dist-info/top_level.txt
salesforce_bulk_python-0.1.0.dist-info/RECORD
