Metadata-Version: 2.1
Name: salesforce-bulk-python
Version: 0.1.0
Summary: Package to communicate with Salesforce using their Bulk REST API v2.0.
Home-page: https://github.com/mrpowerus/salesforce-bulk-python
Author: Mike Pieters
Author-email: me@mikepieters.com
License: UNKNOWN
Project-URL: Bug Tracker, https://github.com/mrpowerus/salesforce-bulk-python/issues
Platform: UNKNOWN
Classifier: Programming Language :: Python :: 3
Classifier: License :: OSI Approved :: GNU General Public License v3 (GPLv3)
Classifier: Operating System :: OS Independent
Requires-Python: >=3.6
License-File: LICENSE
Requires-Dist: pyjwt
Requires-Dist: requests
Requires-Dist: asyncio
Requires-Dist: cryptography
